{
  "9U3EMCIBlyYATLhh9YLnfYwKgpC2": {
    "holdings": [
      {
        "ticker": "AAPL",
        "qty": 10.0,
        "avg_cost": 200.0
      },
      {
        "ticker": "ALAB",
        "qty": 100.0,
        "avg_cost": 76.0
      },
      {
        "ticker": "AMD",
        "qty": 10.0,
        "avg_cost": 265.0
      },
      {
        "ticker": "APLD",
        "qty": 35.0,
        "avg_cost": 46.14
      },
      {
        "ticker": "APP",
        "qty": 200.0,
        "avg_cost": 423.0
      },
      {
        "ticker": "DRAM",
        "qty": 100.0,
        "avg_cost": 45.0
      },
      {
        "ticker": "GOOGL",
        "qty": 100.0,
        "avg_cost": 215.0
      },
      {
        "ticker": "GS",
        "qty": 100.0,
        "avg_cost": 670.0
      },
      {
        "ticker": "HOOD",
        "qty": 100.0,
        "avg_cost": 91.17
      },
      {
        "ticker": "INTC",
        "qty": 100.0,
        "avg_cost": 45.0
      },
      {
        "ticker": "IREN",
        "qty": 1.0,
        "avg_cost": 45.0
      },
      {
        "ticker": "LRCX",
        "qty": 10.0,
        "avg_cost": 289.0
      },
      {
        "ticker": "LUNR",
        "qty": 100.0,
        "avg_cost": 20.0
      },
      {
        "ticker": "MSFT",
        "qty": 45.0,
        "avg_cost": 345.0
      },
      {
        "ticker": "MU",
        "qty": 10.0,
        "avg_cost": 245.0
      },
      {
        "ticker": "NVDA",
        "qty": 100.0,
        "avg_cost": 165.0
      },
      {
        "ticker": "ORCL",
        "qty": 10.0,
        "avg_cost": 100.0
      },
      {
        "ticker": "PLTR",
        "qty": 100.0,
        "avg_cost": 120.0
      },
      {
        "ticker": "QBTS",
        "qty": 1000.0,
        "avg_cost": 4.66
      },
      {
        "ticker": "QLD",
        "qty": 50.0,
        "avg_cost": 51.0
      },
      {
        "ticker": "RBRK",
        "qty": 246.0,
        "avg_cost": 56.0
      },
      {
        "ticker": "RGTI",
        "qty": 300.0,
        "avg_cost": 6.0
      },
      {
        "ticker": "RKLB",
        "qty": 200.0,
        "avg_cost": 21.0
      },
      {
        "ticker": "SMCI",
        "qty": 100.0,
        "avg_cost": 23.0
      },
      {
        "ticker": "SNDK",
        "qty": 10.0,
        "avg_cost": 450.0
      },
      {
        "ticker": "SNOW",
        "qty": 35.0,
        "avg_cost": 240.0
      },
      {
        "ticker": "SSO",
        "qty": 50.0,
        "avg_cost": 44.0
      },
      {
        "ticker": "TSLA",
        "qty": 100.0,
        "avg_cost": 439.0
      },
      {
        "ticker": "TSM",
        "qty": 100.0,
        "avg_cost": 175.0
      },
      {
        "ticker": "VRT",
        "qty": 1.0,
        "avg_cost": 16.0
      }
    ]
  },
  "9XYERwojDqZYyeKV2ajvWQig8Bh2": {
    "holdings": [
      {
        "ticker": "AAPL",
        "qty": 10.0,
        "avg_cost": 250.0
      }
    ]
  },
  "RWaiB5nNl5TjiWamTOEMb8tgVgQ2": {
    "holdings": [
      {
        "ticker": "AAPL",
        "qty": 5.0,
        "avg_cost": 240.0
      },
      {
        "ticker": "GS",
        "qty": 3.0,
        "avg_cost": 800.0
      },
      {
        "ticker": "MNST",
        "qty": 5.0,
        "avg_cost": 80.0
      },
      {
        "ticker": "SPCX",
        "qty": 5.0,
        "avg_cost": 160.95
      },
      {
        "ticker": "TSLA",
        "qty": 15.0,
        "avg_cost": 250.0
      }
    ]
  },
  "WwfbUgQdviVtfrB3BBzR25joqbv2": {
    "holdings": [
      {
        "ticker": "AAPL",
        "qty": 4.0,
        "avg_cost": 250.0
      },
      {
        "ticker": "AMAT",
        "qty": 5.0,
        "avg_cost": 140.0
      },
      {
        "ticker": "AMZN",
        "qty": 3.0,
        "avg_cost": 250.0
      },
      {
        "ticker": "COIN",
        "qty": 5.0,
        "avg_cost": 80.0
      },
      {
        "ticker": "DTE",
        "qty": 4.0,
        "avg_cost": 100.0
      },
      {
        "ticker": "EOG",
        "qty": 1.0,
        "avg_cost": 11.0
      },
      {
        "ticker": "FICO",
        "qty": 2.0,
        "avg_cost": 760.0
      },
      {
        "ticker": "GS",
        "qty": 20.0,
        "avg_cost": 140.0
      },
      {
        "ticker": "INTC",
        "qty": 35.0,
        "avg_cost": 44.29
      },
      {
        "ticker": "NVDA",
        "qty": 10.0,
        "avg_cost": 280.0
      },
      {
        "ticker": "NXPI",
        "qty": 2.0,
        "avg_cost": 285.2
      },
      {
        "ticker": "SIRI",
        "qty": 10.0,
        "avg_cost": 80.0
      },
      {
        "ticker": "SNDK",
        "qty": 35.0,
        "avg_cost": 5.45
      },
      {
        "ticker": "TSLA",
        "qty": 5.0,
        "avg_cost": 400.0
      },
      {
        "ticker": "WDC",
        "qty": 3.0,
        "avg_cost": 500.01
      }
    ]
  },
  "XywlmmAEAhN9JBDkYQnagsBIkCf1": {
    "holdings": [
      {
        "ticker": "BTC-USD",
        "qty": 2.0,
        "avg_cost": 1000.0
      },
      {
        "ticker": "GS",
        "qty": 5.0,
        "avg_cost": 500.0
      }
    ]
  }
}